<PubmedArticleSet>
<PubmedArticle>
    <MedlineCitation Owner="NLM" Status="MEDLINE">
        <PMID Version="1">18323547</PMID>
        <DateCompleted>
            <Year>2008</Year>
            <Month>04</Month>
            <Day>08</Day>
        </DateCompleted>
        <DateRevised>
            <Year>2008</Year>
            <Month>03</Month>
            <Day>07</Day>
        </DateRevised>
        <Article PubModel="Print">
            <Journal>
                <ISSN IssnType="Electronic">1527-7755</ISSN>
                <JournalIssue CitedMedium="Internet">
                    <Volume>26</Volume>
                    <Issue>8</Issue>
                    <PubDate>
                        <Year>2008</Year>
                        <Month>Mar</Month>
                        <Day>10</Day>
                    </PubDate>
                </JournalIssue>
                <Title>Journal of clinical oncology : official journal of the American Society of Clinical Oncology</Title>
                <ISOAbbreviation>J Clin Oncol</ISOAbbreviation>
            </Journal>
            <ArticleTitle>Risk of new primary nonbreast cancers after breast cancer treatment: a Dutch population-based study.</ArticleTitle>
            <Pagination>
                <MedlinePgn>1239-46</MedlinePgn>
            </Pagination>
            <ELocationID EIdType="doi" ValidYN="Y">10.1200/JCO.2007.11.9081</ELocationID>
            <Abstract>
                <AbstractText Label="PURPOSE" NlmCategory="OBJECTIVE">To assess the risk of secondary nonbreast cancers (SNBCs) in a recently treated population-based cohort of breast cancer patients focused on the association with treatment and prognostic implications.</AbstractText>
                <AbstractText Label="PATIENTS AND METHODS" NlmCategory="METHODS">In 58,068 Dutch patients diagnosed with invasive breast cancer between 1989 and 2003, SNBC risk was quantified using standardized incidence ratios (SIRs), cumulative incidence, and Cox regression analysis, adjusted for competing risks.</AbstractText>
                <AbstractText Label="RESULTS" NlmCategory="RESULTS">After a median follow-up of 5.4 years, 2,578 SNBCs had occurred. Compared with the Dutch female population at large, in this cohort, the SIR of SNBCs was increased (SIR, 1.22; 95% CI, 1.17 to 1.27). The absolute excess risk was 13.6 (95% CI, 9.7 to 17.6) per 10,000 person-years. SIRs were elevated for cancers of the esophagus, stomach, colon, rectum, lung, uterus, ovary, kidney, and bladder cancers, and for soft tissue sarcomas (STS), melanoma, non-Hodgkin's lymphoma, and acute myeloid leukemia (AML). The 10-year cumulative incidence of SNBCs was 5.4% (95% CI, 5.1% to 5.7%). Among patients younger than 50 years, radiotherapy was associated with an increased lung cancer risk (hazard ratio [HR] = 2.31; 95% CI, 1.15 to 4.60) and chemotherapy with decreased risk for all SNBCs (HR = 0.78; 95% CI, 0.63 to 0.98) and for colon and lung cancer. Among patients age 50 years and older, radiotherapy was associated with raised STS risk (HR = 3.43; 95% CI, 1.46 to 8.04); chemotherapy with increased risks of melanoma, uterine cancer, and AML; and hormonal therapy with all SNBCs combined (HR = 1.10; 95% CI, 1.01 to 1.21) and uterine cancer (HR = 1.78; 95% CI, 1.40 to 2.27). An SNBC worsened survival (HR = 3.98; 95%CI 3.77 to 4.20).</AbstractText>
                <AbstractText Label="CONCLUSION" NlmCategory="CONCLUSIONS">Breast cancer patients diagnosed in the 1990 s experienced a small but significant excess risk of developing an SNBC.</AbstractText>
            </Abstract>
            <AuthorList CompleteYN="Y">
                <Author ValidYN="Y">
                    <LastName>Schaapveld</LastName>
                    <ForeName>Michael</ForeName>
                    <Initials>M</Initials>
                    <AffiliationInfo>
                        <Affiliation>Comprehensive Cancer Center North-Netherlands (CCCN), P.O. Box 330, 9700 AH Groningen, The Netherlands. m.schaapveld@ikn.nl</Affiliation>
                    </AffiliationInfo>
                </Author>
                <Author ValidYN="Y">
                    <LastName>Visser</LastName>
                    <ForeName>Otto</ForeName>
                    <Initials>O</Initials>
                </Author>
                <Author ValidYN="Y">
                    <LastName>Louwman</LastName>
                    <ForeName>Marieke J</ForeName>
                    <Initials>MJ</Initials>
                </Author>
                <Author ValidYN="Y">
                    <LastName>de Vries</LastName>
                    <ForeName>Elisabeth G E</ForeName>
                    <Initials>EG</Initials>
                </Author>
                <Author ValidYN="Y">
                    <LastName>Willemse</LastName>
                    <ForeName>Pax H B</ForeName>
                    <Initials>PH</Initials>
                </Author>
                <Author ValidYN="Y">
                    <LastName>Otter</LastName>
                    <ForeName>Ren&#233;e</ForeName>
                    <Initials>R</Initials>
                </Author>
                <Author ValidYN="Y">
                    <LastName>van der Graaf</LastName>
                    <ForeName>Winette T A</ForeName>
                    <Initials>WT</Initials>
                </Author>
                <Author ValidYN="Y">
                    <LastName>Coebergh</LastName>
                    <ForeName>Jan-Willem W</ForeName>
                    <Initials>JW</Initials>
                </Author>
                <Author ValidYN="Y">
                    <LastName>van Leeuwen</LastName>
                    <ForeName>Flora E</ForeName>
                    <Initials>FE</Initials>
                </Author>
            </AuthorList>
            <Language>eng</Language>
            <PublicationTypeList>
                <PublicationType UI="D016428">Journal Article</PublicationType>
                <PublicationType UI="D016448">Multicenter Study</PublicationType>
            </PublicationTypeList>
        </Article>
        <MedlineJournalInfo>
            <Country>United States</Country>
            <MedlineTA>J Clin Oncol</MedlineTA>
            <NlmUniqueID>8309333</NlmUniqueID>
            <ISSNLinking>0732-183X</ISSNLinking>
        </MedlineJournalInfo>
        <CitationSubset>IM</CitationSubset>
        <MeshHeadingList>
            <MeshHeading>
                <DescriptorName MajorTopicYN="N" UI="D000328">Adult</DescriptorName>
            </MeshHeading>
            <MeshHeading>
                <DescriptorName MajorTopicYN="N" UI="D000368">Aged</DescriptorName>
            </MeshHeading>
            <MeshHeading>
                <DescriptorName MajorTopicYN="N" UI="D000369">Aged, 80 and over</DescriptorName>
            </MeshHeading>
            <MeshHeading>
                <DescriptorName MajorTopicYN="N" UI="D001943">Breast Neoplasms</DescriptorName>
                <QualifierName MajorTopicYN="N" UI="Q000175">diagnosis</QualifierName>
                <QualifierName MajorTopicYN="Y" UI="Q000628">therapy</QualifierName>
            </MeshHeading>
            <MeshHeading>
                <DescriptorName MajorTopicYN="N" UI="D017024">Chemotherapy, Adjuvant</DescriptorName>
            </MeshHeading>
            <MeshHeading>
                <DescriptorName MajorTopicYN="N" UI="D015331">Cohort Studies</DescriptorName>
            </MeshHeading>
            <MeshHeading>
                <DescriptorName MajorTopicYN="N" UI="D003131">Combined Modality Therapy</DescriptorName>
            </MeshHeading>
            <MeshHeading>
                <DescriptorName MajorTopicYN="N" UI="D005260">Female</DescriptorName>
            </MeshHeading>
            <MeshHeading>
                <DescriptorName MajorTopicYN="N" UI="D005500">Follow-Up Studies</DescriptorName>
            </MeshHeading>
            <MeshHeading>
                <DescriptorName MajorTopicYN="N" UI="D006801">Humans</DescriptorName>
            </MeshHeading>
            <MeshHeading>
                <DescriptorName MajorTopicYN="N" UI="D015994">Incidence</DescriptorName>
            </MeshHeading>
            <MeshHeading>
                <DescriptorName MajorTopicYN="N" UI="D008875">Middle Aged</DescriptorName>
            </MeshHeading>
            <MeshHeading>
                <DescriptorName MajorTopicYN="N" UI="D016609">Neoplasms, Second Primary</DescriptorName>
                <QualifierName MajorTopicYN="N" UI="Q000453">epidemiology</QualifierName>
                <QualifierName MajorTopicYN="Y" UI="Q000209">etiology</QualifierName>
            </MeshHeading>
            <MeshHeading>
                <DescriptorName MajorTopicYN="N" Type="Geographic" UI="D009426">Netherlands</DescriptorName>
                <QualifierName MajorTopicYN="N" UI="Q000453">epidemiology</QualifierName>
            </MeshHeading>
            <MeshHeading>
                <DescriptorName MajorTopicYN="N" UI="D012307">Risk Factors</DescriptorName>
            </MeshHeading>
            <MeshHeading>
                <DescriptorName MajorTopicYN="N" UI="D015996">Survival Rate</DescriptorName>
            </MeshHeading>
        </MeshHeadingList>
    </MedlineCitation>
    <PubmedData>
        <History>
            <PubMedPubDate PubStatus="pubmed">
                <Year>2008</Year>
                <Month>3</Month>
                <Day>8</Day>
                <Hour>9</Hour>
                <Minute>0</Minute>
            </PubMedPubDate>
            <PubMedPubDate PubStatus="medline">
                <Year>2008</Year>
                <Month>4</Month>
                <Day>9</Day>
                <Hour>9</Hour>
                <Minute>0</Minute>
            </PubMedPubDate>
            <PubMedPubDate PubStatus="entrez">
                <Year>2008</Year>
                <Month>3</Month>
                <Day>8</Day>
                <Hour>9</Hour>
                <Minute>0</Minute>
            </PubMedPubDate>
        </History>
        <PublicationStatus>ppublish</PublicationStatus>
        <ArticleIdList>
            <ArticleId IdType="pubmed">18323547</ArticleId>
            <ArticleId IdType="pii">26/8/1239</ArticleId>
            <ArticleId IdType="doi">10.1200/JCO.2007.11.9081</ArticleId>
        </ArticleIdList>
    </PubmedData>
</PubmedArticle>

</PubmedArticleSet>